groggy-0.5.2.dist-info/METADATA
groggy-0.5.2.dist-info/WHEEL
groggy-0.5.2.dist-info/licenses/LICENSE
groggy/__init__.py
groggy/__init__.pyi
groggy/_frontend.py
groggy/_groggy.cp39-win_amd64.pyd
groggy/_groggy.pyi
groggy/algorithms/__init__.py
groggy/algorithms/base.py
groggy/algorithms/centrality.py
groggy/algorithms/community.py
groggy/algorithms/pathfinding.py
groggy/builder.py
groggy/builder.pyi
groggy/builder/__init__.py
groggy/builder/algorithm_builder.py
groggy/builder/decorators.py
groggy/builder/examples.py
groggy/builder/examples.py.bak
groggy/builder/execution/__init__.py
groggy/builder/execution/context.py
groggy/builder/ir/__init__.py
groggy/builder/ir/analysis.py
groggy/builder/ir/batch.py
groggy/builder/ir/graph.py
groggy/builder/ir/memory.py
groggy/builder/ir/nodes.py
groggy/builder/ir/optimizer.py
groggy/builder/ir/parallel.py
groggy/builder/traits/__init__.py
groggy/builder/traits/attr.py
groggy/builder/traits/core.py
groggy/builder/traits/graph.py
groggy/builder/traits/iter.py
groggy/builder/varhandle.py
groggy/builder_original.py
groggy/display/README.md
groggy/display/__init__.py
groggy/display/array_display.py
groggy/display/demo.py
groggy/display/formatters.py
groggy/display/integration_example.py
groggy/display/matrix_display.py
groggy/display/table_display.py
groggy/display/test_simple.py
groggy/display/truncation.py
groggy/display/unicode_chars.py
groggy/enhanced_query.py
groggy/errors.py
groggy/examples.py
groggy/expr_parser.py
groggy/generators.py
groggy/graph.py
groggy/imports.py
groggy/jupyter_utils.py
groggy/labextension/core.d.ts
groggy/labextension/extension.d.ts
groggy/labextension/index.d.ts
groggy/labextension/index.js
groggy/labextension/index.js.map
groggy/labextension/package.json
groggy/labextension/plugin.d.ts
groggy/labextension/plugin.js
groggy/labextension/plugin.js.map
groggy/labextension/widget.d.ts
groggy/nbextension/index.js
groggy/nbextension/index.js.map
groggy/networkx_compat.py
groggy/pipeline.py
groggy/static/__init__.py
groggy/static/groggy-viz-core.standalone.js
groggy/static/groggy-widget.js
groggy-0.5.2.dist-info/RECORD
