Metadata-Version: 2.4
Name: groggy
Version: 0.5.2
Classifier: Development Status :: 3 - Alpha
Classifier: Intended Audience :: Developers
Classifier: License :: OSI Approved :: MIT License
Classifier: Programming Language :: Python :: 3
Classifier: Programming Language :: Python :: 3.8
Classifier: Programming Language :: Python :: 3.9
Classifier: Programming Language :: Python :: 3.10
Classifier: Programming Language :: Python :: 3.11
Classifier: Programming Language :: Python :: 3.12
Classifier: Programming Language :: Rust
Classifier: Topic :: Scientific/Engineering
Classifier: Topic :: Software Development :: Libraries :: Python Modules
Requires-Dist: typing-extensions>=4.0.0
Requires-Dist: pytest>=6.0 ; extra == 'dev'
Requires-Dist: pytest-benchmark ; extra == 'dev'
Requires-Dist: networkx ; extra == 'dev'
Requires-Dist: numpy ; extra == 'dev'
Requires-Dist: matplotlib ; extra == 'dev'
Requires-Dist: sphinx>=7.0.0 ; extra == 'docs'
Requires-Dist: sphinx-rtd-theme>=1.3.0 ; extra == 'docs'
Requires-Dist: myst-parser>=2.0.0 ; extra == 'docs'
Requires-Dist: sphinx-autobuild>=2021.3.14 ; extra == 'docs'
Requires-Dist: sphinx-copybutton>=0.5.2 ; extra == 'docs'
Requires-Dist: sphinx-autoapi>=3.0.0 ; extra == 'docs'
Requires-Dist: pygments>=2.15.0 ; extra == 'docs'
Provides-Extra: dev
Provides-Extra: docs
License-File: LICENSE
Summary: Groggy - A Graph Language Engine for dynamic graphs and versioned state
Keywords: graph,network,data-structure,algorithms
Author: Groggy Contributors
License: MIT
Requires-Python: >=3.8
Project-URL: Homepage, https://github.com/rollingstorms/groggy
Project-URL: Repository, https://github.com/rollingstorms/groggy
Project-URL: Documentation, https://groggy.readthedocs.io
